{"filename": "2009_002057.jpg", "src_database": "The VOC2009 Database", "src_annotation": "PASCAL VOC2009", "src_image": "flickr", "image_width": 500, "image_height": 377, "image_depth": 3, "category": "bus", "pose": "Unspecified", "truncated": 0, "occluded": 0, "difficult": 0, "bndbox": [167, 164, 368, 291], "kps": {"0": [260, 207], "1": [362, 208], "2": [292, 261], "3": [352, 262], "4": [323, 278], "5": null, "6": null, "7": null, "8": null, "9": null, "10": [178, 261], "11": [186, 262], "12": [192, 266], "13": [233, 274], "14": [245, 271], "15": [252, 280], "16": [274, 284], "17": [360, 282], "18": [272, 180], "19": [354, 182], "20": null, "21": null, "22": null, "23": null, "24": null, "25": null, "26": [171, 257], "27": null, "28": [175, 191], "29": null}, "azimuth_id": 7}