{"filename": "2009_000209.jpg", "src_database": "The VOC2009 Database", "src_annotation": "PASCAL VOC2009", "src_image": "flickr", "image_width": 375, "image_height": 500, "image_depth": 3, "category": "chair", "pose": "Left", "truncated": 0, "occluded": 0, "difficult": 0, "bndbox": [115, 209, 315, 475], "kps": {"0": [128, 310], "1": [120, 332], "2": [234, 323], "3": [248, 337], "4": null, "5": [119, 458], "6": null, "7": [272, 466], "8": [271, 217], "9": [287, 225], "10": [181, 267], "11": null, "12": [240, 288], "13": null, "14": null, "15": null, "16": null, "17": null, "18": null, "19": null, "20": null, "21": null, "22": null, "23": null, "24": null, "25": null, "26": null, "27": null, "28": null, "29": null}, "azimuth_id": 1}