{"filename": "2009_000592.jpg", "src_database": "The VOC2009 Database", "src_annotation": "PASCAL VOC2009", "src_image": "flickr", "image_width": 500, "image_height": 334, "image_depth": 3, "category": "train", "pose": "Unspecified", "truncated": 0, "occluded": 0, "difficult": 0, "bndbox": [144, 177, 400, 295], "kps": {"0": [373, 180], "1": [325, 178], "2": [389, 252], "3": [328, 251], "4": null, "5": [142, 253], "6": null, "7": [140, 267], "8": [384, 194], "9": [315, 198], "10": [385, 211], "11": [316, 213], "12": [375, 196], "13": [325, 194], "14": [378, 212], "15": [325, 212], "16": null, "17": null, "18": null, "19": null, "20": null, "21": null, "22": null, "23": null, "24": null, "25": null, "26": null, "27": null, "28": null, "29": null}, "azimuth_id": 7}