{"filename": "2009_000120.jpg", "src_database": "The VOC2009 Database", "src_annotation": "PASCAL VOC2009", "src_image": "flickr", "image_width": 367, "image_height": 500, "image_depth": 3, "category": "boat", "pose": "Left", "truncated": 0, "occluded": 0, "difficult": 0, "bndbox": [6, 48, 293, 441], "kps": {"0": [37, 423], "1": null, "2": [105, 426], "3": null, "4": [191, 428], "5": null, "6": [287, 427], "7": null, "8": [107, 437], "9": null, "10": [193, 438], "11": null, "12": [288, 435], "13": [38, 436], "14": null, "15": null, "16": null, "17": null, "18": null, "19": null, "20": null, "21": null, "22": null, "23": null, "24": null, "25": null, "26": null, "27": null, "28": null, "29": null}, "azimuth_id": 2}