{"pair_id": 734, "filename": "000734-2008_006951-2009_005215:aeroplane", "src_imname": "2008_006951.jpg", "trg_imname": "2009_005215.jpg", "src_imsize": [500, 333, 3], "trg_imsize": [500, 332, 3], "src_bndbox": [128, 102, 472, 207], "trg_bndbox": [35, 78, 464, 219], "category": "aeroplane", "src_pose": "Left", "trg_pose": "Unspecified", "src_kps": [[130, 182], [140, 172], [163, 163], [167, 203], [256, 191], [420, 162], [383, 154], [434, 105]], "trg_kps": [[382, 181], [377, 164], [366, 150], [357, 213], [374, 197], [459, 163], [222, 156], [185, 83]], "kps_ids": ["0", "1", "2", "3", "7", "9", "22", "23"], "mirror": 0, "viewpoint_variation": 1, "scale_variation": 0, "truncation": 0, "occlusion": 0}