{"pair_id": 1133, "filename": "001133-2009_002011-2008_002221:aeroplane", "src_imname": "2009_002011.jpg", "trg_imname": "2008_002221.jpg", "src_imsize": [500, 334, 3], "trg_imsize": [500, 375, 3], "src_bndbox": [1, 17, 491, 300], "trg_bndbox": [121, 125, 381, 254], "category": "aeroplane", "src_pose": "Right", "trg_pose": "Unspecified", "src_kps": [[488, 140], [350, 276]], "trg_kps": [[378, 180], [349, 198]], "kps_ids": ["0", "3"], "mirror": 0, "viewpoint_variation": 0, "scale_variation": 2, "truncation": 1, "occlusion": 0}