{"pair_id": 1443, "filename": "001443-2010_000285-2010_004546:aeroplane", "src_imname": "2010_000285.jpg", "trg_imname": "2010_004546.jpg", "src_imsize": [500, 375, 3], "trg_imsize": [500, 349, 3], "src_bndbox": [140, 110, 317, 243], "trg_bndbox": [1, 16, 500, 326], "category": "aeroplane", "src_pose": "Unspecified", "trg_pose": "Frontal", "src_kps": [[314, 146], [255, 145], [279, 187]], "trg_kps": [[230, 242], [48, 144], [455, 147]], "kps_ids": ["0", "6", "7"], "mirror": 0, "viewpoint_variation": 1, "scale_variation": 2, "truncation": 2, "occlusion": 0}