{"pair_id": 1572, "filename": "001572-2010_001931-2008_004138:aeroplane", "src_imname": "2010_001931.jpg", "trg_imname": "2008_004138.jpg", "src_imsize": [500, 341, 3], "trg_imsize": [500, 375, 3], "src_bndbox": [2, 59, 494, 265], "trg_bndbox": [116, 150, 416, 266], "category": "aeroplane", "src_pose": "Unspecified", "trg_pose": "Unspecified", "src_kps": [[387, 197], [376, 164], [340, 251], [174, 250], [306, 249], [177, 224], [390, 228], [4, 180], [483, 187], [241, 203], [34, 167], [127, 177], [131, 63]], "trg_kps": [[372, 161], [360, 155], [345, 204], [255, 234], [309, 247], [264, 192], [368, 225], [123, 172], [407, 260], [291, 199], [148, 226], [216, 236], [219, 184]], "kps_ids": ["0", "1", "3", "4", "5", "6", "7", "8", "9", "12", "16", "18", "23"], "mirror": 0, "viewpoint_variation": 0, "scale_variation": 1, "truncation": 0, "occlusion": 0}