{"pair_id": 2067, "filename": "002067-2010_003933-2008_007884:aeroplane", "src_imname": "2010_003933.jpg", "trg_imname": "2008_007884.jpg", "src_imsize": [500, 334, 3], "trg_imsize": [500, 318, 3], "src_bndbox": [4, 67, 500, 284], "trg_bndbox": [149, 68, 408, 169], "category": "aeroplane", "src_pose": "Left", "trg_pose": "Left", "src_kps": [[32, 111], [110, 76], [412, 266], [261, 265], [23, 121]], "trg_kps": [[154, 134], [188, 114], [241, 162], [308, 165], [399, 147]], "kps_ids": ["0", "2", "4", "5", "9"], "mirror": 0, "viewpoint_variation": 1, "scale_variation": 2, "truncation": 1, "occlusion": 0}