{"pair_id": 2195, "filename": "002195-2010_004546-2010_003798:aeroplane", "src_imname": "2010_004546.jpg", "trg_imname": "2010_003798.jpg", "src_imsize": [500, 349, 3], "trg_imsize": [500, 375, 3], "src_bndbox": [1, 16, 500, 326], "trg_bndbox": [6, 118, 494, 313], "category": "aeroplane", "src_pose": "Frontal", "trg_pose": "Left", "src_kps": [[249, 26], [246, 296], [455, 147]], "trg_kps": [[47, 237], [57, 299], [58, 282]], "kps_ids": ["2", "3", "7"], "mirror": 0, "viewpoint_variation": 1, "scale_variation": 0, "truncation": 1, "occlusion": 0}