{"pair_id": 2266, "filename": "002266-2010_004791-2011_002470:aeroplane", "src_imname": "2010_004791.jpg", "trg_imname": "2011_002470.jpg", "src_imsize": [500, 321, 3], "trg_imsize": [500, 364, 3], "src_bndbox": [125, 91, 467, 216], "trg_bndbox": [10, 113, 498, 247], "category": "aeroplane", "src_pose": "Left", "trg_pose": "Right", "src_kps": [[126, 184], [153, 163], [153, 211], [444, 178], [360, 193], [460, 160], [358, 156], [420, 94], [415, 165]], "trg_kps": [[491, 176], [424, 147], [435, 218], [206, 183], [293, 212], [39, 200], [111, 188], [26, 119], [17, 213]], "kps_ids": ["0", "2", "3", "8", "10", "16", "22", "23", "24"], "mirror": 0, "viewpoint_variation": 1, "scale_variation": 0, "truncation": 0, "occlusion": 0}