{"pair_id": 3156, "filename": "003156-2008_004101-2009_000457:bicycle", "src_imname": "2008_004101.jpg", "trg_imname": "2009_000457.jpg", "src_imsize": [500, 375, 3], "trg_imsize": [500, 333, 3], "src_bndbox": [92, 240, 260, 375], "trg_bndbox": [4, 144, 267, 321], "category": "bicycle", "src_pose": "Frontal", "trg_pose": "Right", "src_kps": [[122, 330], [124, 251], [247, 273], [196, 275]], "trg_kps": [[60, 261], [115, 158], [161, 150], [163, 167]], "kps_ids": ["1", "2", "3", "4"], "mirror": 0, "viewpoint_variation": 0, "scale_variation": 1, "truncation": 1, "occlusion": 2}