{"pair_id": 3314, "filename": "003314-2008_004995-2008_007222:bicycle", "src_imname": "2008_004995.jpg", "trg_imname": "2008_007222.jpg", "src_imsize": [500, 333, 3], "trg_imsize": [500, 424, 3], "src_bndbox": [27, 144, 216, 330], "trg_bndbox": [126, 179, 308, 418], "category": "bicycle", "src_pose": "Left", "trg_pose": "Right", "src_kps": [[50, 265], [169, 281], [105, 157], [48, 150], [73, 166], [129, 232], [122, 273]], "trg_kps": [[269, 363], [178, 321], [184, 186], [281, 200], [254, 226], [201, 275], [200, 326]], "kps_ids": ["0", "1", "2", "3", "4", "8", "13"], "mirror": 0, "viewpoint_variation": 1, "scale_variation": 0, "truncation": 0, "occlusion": 0}