{"pair_id": 5449, "filename": "005449-2010_004307-2009_001558:bicycle", "src_imname": "2010_004307.jpg", "trg_imname": "2009_001558.jpg", "src_imsize": [335, 500, 3], "trg_imsize": [375, 500, 3], "src_bndbox": [1, 241, 335, 497], "trg_bndbox": [96, 1, 311, 500], "category": "bicycle", "src_pose": "Left", "trg_pose": "Unspecified", "src_kps": [[56, 488], [304, 375], [167, 410], [83, 327], [245, 310], [297, 281], [318, 301], [280, 429]], "trg_kps": [[164, 164], [235, 358], [174, 59], [192, 29], [212, 95], [270, 126], [191, 131], [150, 291]], "kps_ids": ["0", "1", "3", "4", "5", "6", "7", "10"], "mirror": 0, "viewpoint_variation": 1, "scale_variation": 0, "truncation": 1, "occlusion": 1}