{"pair_id": 9131, "filename": "009131-2008_000120-2008_004636:boat", "src_imname": "2008_000120.jpg", "trg_imname": "2008_004636.jpg", "src_imsize": [500, 332, 3], "trg_imsize": [500, 375, 3], "src_bndbox": [21, 53, 408, 253], "trg_bndbox": [1, 174, 330, 375], "category": "boat", "src_pose": "Unspecified", "trg_pose": "Frontal", "src_kps": [[37, 114], [194, 123], [319, 159], [403, 193], [206, 249], [310, 245]], "trg_kps": [[10, 364], [271, 283], [324, 222], [307, 177], [267, 313], [322, 252]], "kps_ids": ["0", "2", "4", "6", "8", "10"], "mirror": 0, "viewpoint_variation": 0, "scale_variation": 0, "truncation": 2, "occlusion": 2}