{"pair_id": 10447, "filename": "010447-2008_006349-2008_005512:boat", "src_imname": "2008_006349.jpg", "trg_imname": "2008_005512.jpg", "src_imsize": [500, 375, 3], "trg_imsize": [500, 375, 3], "src_bndbox": [35, 110, 485, 226], "trg_bndbox": [192, 51, 359, 268], "category": "boat", "src_pose": "Right", "trg_pose": "Left", "src_kps": [[477, 181], [364, 183], [410, 223]], "trg_kps": [[204, 248], [242, 246], [219, 261]], "kps_ids": ["0", "1", "13"], "mirror": 0, "viewpoint_variation": 2, "scale_variation": 0, "truncation": 0, "occlusion": 0}