{"pair_id": 10627, "filename": "010627-2008_007599-2009_002662:boat", "src_imname": "2008_007599.jpg", "trg_imname": "2009_002662.jpg", "src_imsize": [500, 375, 3], "trg_imsize": [500, 333, 3], "src_bndbox": [46, 90, 424, 279], "trg_bndbox": [71, 38, 480, 183], "category": "boat", "src_pose": "Left", "trg_pose": "Left", "src_kps": [[58, 209], [200, 215], [407, 180], [206, 270], [332, 266], [416, 259], [109, 273]], "trg_kps": [[80, 91], [266, 126], [463, 78], [265, 166], [388, 141], [459, 99], [101, 171]], "kps_ids": ["0", "2", "6", "8", "10", "12", "13"], "mirror": 0, "viewpoint_variation": 0, "scale_variation": 0, "truncation": 0, "occlusion": 0}