{"pair_id": 10851, "filename": "010851-2009_000830-2010_000887:boat", "src_imname": "2009_000830.jpg", "trg_imname": "2010_000887.jpg", "src_imsize": [500, 326, 3], "trg_imsize": [500, 357, 3], "src_bndbox": [101, 23, 387, 299], "trg_bndbox": [218, 85, 424, 245], "category": "boat", "src_pose": "Left", "trg_pose": "Rear", "src_kps": [[165, 278], [229, 291], [294, 292], [341, 281], [361, 285], [358, 292]], "trg_kps": [[396, 95], [309, 129], [265, 154], [323, 202], [226, 184], [231, 226]], "kps_ids": ["0", "2", "4", "5", "6", "12"], "mirror": 0, "viewpoint_variation": 1, "scale_variation": 1, "truncation": 0, "occlusion": 0}