{"pair_id": 13294, "filename": "013294-2009_002060-2010_001219:bottle", "src_imname": "2009_002060.jpg", "trg_imname": "2010_001219.jpg", "src_imsize": [500, 375, 3], "trg_imsize": [333, 500, 3], "src_bndbox": [185, 1, 320, 365], "trg_bndbox": [127, 68, 234, 357], "category": "bottle", "src_pose": "Unspecified", "trg_pose": "Unspecified", "src_kps": [[254, 18], [227, 20], [292, 48], [194, 59], [307, 185], [204, 197], [307, 325], [224, 336]], "trg_kps": [[178, 120], [153, 120], [192, 159], [136, 160], [208, 252], [152, 258], [223, 336], [164, 344]], "kps_ids": ["2", "3", "4", "5", "6", "7", "8", "9"], "mirror": 0, "viewpoint_variation": 0, "scale_variation": 0, "truncation": 0, "occlusion": 0}