{"pair_id": 14738, "filename": "014738-2008_002451-2010_004558:bus", "src_imname": "2008_002451.jpg", "trg_imname": "2010_004558.jpg", "src_imsize": [500, 375, 3], "trg_imsize": [333, 500, 3], "src_bndbox": [336, 100, 500, 238], "trg_bndbox": [111, 205, 312, 344], "category": "bus", "src_pose": "Right", "trg_pose": "Frontal", "src_kps": [[443, 216], [469, 221], [344, 118]], "trg_kps": [[132, 299], [139, 297], [118, 248]], "kps_ids": ["11", "12", "28"], "mirror": 0, "viewpoint_variation": 0, "scale_variation": 0, "truncation": 1, "occlusion": 1}