{"pair_id": 15005, "filename": "015005-2008_007356-2008_008113:bus", "src_imname": "2008_007356.jpg", "trg_imname": "2008_008113.jpg", "src_imsize": [500, 325, 3], "trg_imsize": [500, 375, 3], "src_bndbox": [27, 44, 334, 280], "trg_bndbox": [132, 94, 466, 289], "category": "bus", "src_pose": "Frontal", "trg_pose": "Left", "src_kps": [[328, 104], [326, 242], [320, 64], [289, 261], [32, 210], [39, 93]], "trg_kps": [[120, 177], [137, 239], [158, 128], [160, 247], [460, 248], [444, 103]], "kps_ids": ["1", "17", "19", "24", "26", "28"], "mirror": 0, "viewpoint_variation": 2, "scale_variation": 0, "truncation": 0, "occlusion": 0}