{"pair_id": 15379, "filename": "015379-2009_000104-2008_007969:bus", "src_imname": "2009_000104.jpg", "trg_imname": "2008_007969.jpg", "src_imsize": [500, 333, 3], "trg_imsize": [500, 375, 3], "src_bndbox": [57, 49, 439, 219], "trg_bndbox": [1, 1, 500, 375], "category": "bus", "src_pose": "Left", "trg_pose": "Right", "src_kps": [[57, 96], [100, 188], [62, 185], [152, 198], [81, 64], [172, 58]], "trg_kps": [[145, 78], [371, 335], [200, 348], [486, 326], [203, 3], [428, 22]], "kps_ids": ["0", "4", "16", "17", "18", "19"], "mirror": 0, "viewpoint_variation": 0, "scale_variation": 1, "truncation": 2, "occlusion": 0}