{"pair_id": 16714, "filename": "016714-2010_004616-2009_005201:bus", "src_imname": "2010_004616.jpg", "trg_imname": "2009_005201.jpg", "src_imsize": [500, 375, 3], "trg_imsize": [500, 375, 3], "src_bndbox": [1, 84, 460, 375], "trg_bndbox": [18, 68, 486, 295], "category": "bus", "src_pose": "Left", "trg_pose": "Right", "src_kps": [[448, 317], [393, 89]], "trg_kps": [[22, 252], [31, 93]], "kps_ids": ["27", "29"], "mirror": 0, "viewpoint_variation": 1, "scale_variation": 0, "truncation": 1, "occlusion": 0}