{"pair_id": 17872, "filename": "017872-2008_003888-2008_007364:car", "src_imname": "2008_003888.jpg", "trg_imname": "2008_007364.jpg", "src_imsize": [400, 284, 3], "trg_imsize": [500, 375, 3], "src_bndbox": [13, 107, 395, 227], "trg_bndbox": [43, 62, 425, 327], "category": "car", "src_pose": "Left", "trg_pose": "Unspecified", "src_kps": [[377, 164], [326, 166], [364, 191], [157, 113], [325, 136], [224, 115]], "trg_kps": [[235, 263], [67, 216], [140, 230], [278, 62], [276, 184], [169, 82]], "kps_ids": ["6", "7", "8", "19", "26", "29"], "mirror": 0, "viewpoint_variation": 1, "scale_variation": 1, "truncation": 0, "occlusion": 1}