{"pair_id": 18249, "filename": "018249-2008_006885-2008_003888:car", "src_imname": "2008_006885.jpg", "trg_imname": "2008_003888.jpg", "src_imsize": [500, 185, 3], "trg_imsize": [400, 284, 3], "src_bndbox": [68, 53, 433, 154], "trg_bndbox": [13, 107, 395, 227], "category": "car", "src_pose": "Left", "trg_pose": "Left", "src_kps": [[240, 80], [218, 83], [266, 57], [363, 126], [330, 135], [165, 129], [127, 133]], "trg_kps": [[117, 144], [109, 144], [157, 113], [241, 200], [216, 202], [64, 194], [42, 194]], "kps_ids": ["1", "17", "19", "21", "22", "24", "25"], "mirror": 0, "viewpoint_variation": 0, "scale_variation": 0, "truncation": 0, "occlusion": 2}