{"pair_id": 18480, "filename": "018480-2008_007825-2009_002387:car", "src_imname": "2008_007825.jpg", "trg_imname": "2009_002387.jpg", "src_imsize": [500, 406, 3], "trg_imsize": [500, 305, 3], "src_bndbox": [22, 144, 455, 304], "trg_bndbox": [76, 117, 438, 264], "category": "car", "src_pose": "Left", "trg_pose": "Right", "src_kps": [[45, 252], [225, 161]], "trg_kps": [[429, 196], [303, 142]], "kps_ids": ["3", "19"], "mirror": 0, "viewpoint_variation": 1, "scale_variation": 0, "truncation": 0, "occlusion": 0}