{"pair_id": 19400, "filename": "019400-2010_000466-2009_004340:car", "src_imname": "2010_000466.jpg", "trg_imname": "2009_004340.jpg", "src_imsize": [500, 333, 3], "trg_imsize": [500, 333, 3], "src_bndbox": [15, 92, 382, 235], "trg_bndbox": [85, 45, 413, 286], "category": "car", "src_pose": "Unspecified", "trg_pose": "Rear", "src_kps": [[106, 131], [363, 157], [264, 159], [326, 186], [323, 221], [187, 199], [328, 133], [249, 137], [279, 106], [207, 110]], "trg_kps": [[115, 108], [375, 193], [121, 190], [247, 218], [385, 256], [110, 257], [359, 107], [137, 103], [340, 57], [156, 60]], "kps_ids": ["1", "6", "7", "8", "11", "21", "26", "27", "28", "29"], "mirror": 0, "viewpoint_variation": 1, "scale_variation": 0, "truncation": 0, "occlusion": 0}