{"pair_id": 20269, "filename": "020269-2010_005907-2010_004291:car", "src_imname": "2010_005907.jpg", "trg_imname": "2010_004291.jpg", "src_imsize": [500, 333, 3], "trg_imsize": [500, 375, 3], "src_bndbox": [14, 10, 479, 309], "trg_bndbox": [71, 124, 458, 274], "category": "car", "src_pose": "Unspecified", "trg_pose": "Right", "src_kps": [[270, 35], [465, 155], [245, 16]], "trg_kps": [[309, 177], [79, 182], [281, 138]], "kps_ids": ["0", "6", "18"], "mirror": 0, "viewpoint_variation": 1, "scale_variation": 1, "truncation": 0, "occlusion": 0}