{"pair_id": 20321, "filename": "020321-2011_000086-2010_004258:car", "src_imname": "2011_000086.jpg", "trg_imname": "2010_004258.jpg", "src_imsize": [500, 375, 3], "trg_imsize": [500, 375, 3], "src_bndbox": [62, 124, 446, 293], "trg_bndbox": [272, 130, 495, 307], "category": "car", "src_pose": "Left", "trg_pose": "Frontal", "src_kps": [[142, 174], [131, 175], [183, 150], [97, 213], [379, 172], [330, 141], [280, 155]], "trg_kps": [[468, 183], [456, 191], [430, 141], [473, 290], [281, 171], [296, 135], [406, 130]], "kps_ids": ["1", "17", "19", "24", "26", "28", "29"], "mirror": 0, "viewpoint_variation": 1, "scale_variation": 0, "truncation": 0, "occlusion": 0}