{"pair_id": 20710, "filename": "020710-2008_001640-2010_000576:cat", "src_imname": "2008_001640.jpg", "trg_imname": "2010_000576.jpg", "src_imsize": [500, 375, 3], "trg_imsize": [500, 429, 3], "src_bndbox": [159, 5, 465, 200], "trg_bndbox": [23, 33, 460, 423], "category": "cat", "src_pose": "Frontal", "trg_pose": "Unspecified", "src_kps": [[181, 48], [250, 55], [165, 13], [267, 20], [184, 74], [230, 79], [197, 102], [203, 102], [201, 112], [208, 179], [255, 187], [452, 168]], "trg_kps": [[61, 83], [160, 92], [43, 37], [190, 53], [76, 136], [146, 140], [103, 153], [111, 153], [108, 171], [87, 373], [92, 416], [432, 164]], "kps_ids": ["0", "1", "2", "3", "4", "5", "6", "7", "8", "9", "10", "13"], "mirror": 0, "viewpoint_variation": 0, "scale_variation": 1, "truncation": 0, "occlusion": 0}