{"pair_id": 21194, "filename": "021194-2008_006325-2010_005853:cat", "src_imname": "2008_006325.jpg", "trg_imname": "2010_005853.jpg", "src_imsize": [500, 476, 3], "trg_imsize": [336, 500, 3], "src_bndbox": [22, 9, 471, 462], "trg_bndbox": [8, 9, 300, 500], "category": "cat", "src_pose": "Right", "trg_pose": "Frontal", "src_kps": [[308, 78], [420, 78], [304, 18], [450, 38], [350, 126], [401, 131], [375, 163], [386, 166], [376, 178], [289, 396], [314, 384]], "trg_kps": [[121, 51], [186, 53], [100, 21], [201, 13], [132, 86], [171, 85], [144, 115], [155, 115], [152, 126], [160, 390], [198, 386]], "kps_ids": ["0", "1", "2", "3", "4", "5", "6", "7", "8", "9", "10"], "mirror": 0, "viewpoint_variation": 1, "scale_variation": 0, "truncation": 0, "occlusion": 0}