{"pair_id": 21383, "filename": "021383-2008_007726-2008_005699:cat", "src_imname": "2008_007726.jpg", "trg_imname": "2008_005699.jpg", "src_imsize": [500, 332, 3], "trg_imsize": [380, 500, 3], "src_bndbox": [66, 54, 481, 316], "trg_bndbox": [1, 60, 321, 500], "category": "cat", "src_pose": "Left", "trg_pose": "Rear", "src_kps": [[117, 68], [267, 62]], "trg_kps": [[287, 68], [196, 63]], "kps_ids": ["2", "3"], "mirror": 0, "viewpoint_variation": 2, "scale_variation": 0, "truncation": 2, "occlusion": 1}