{"pair_id": 21487, "filename": "021487-2009_002228-2011_000973:cat", "src_imname": "2009_002228.jpg", "trg_imname": "2011_000973.jpg", "src_imsize": [376, 500, 3], "trg_imsize": [500, 488, 3], "src_bndbox": [61, 36, 273, 474], "trg_bndbox": [48, 64, 359, 458], "category": "cat", "src_pose": "Frontal", "trg_pose": "Unspecified", "src_kps": [[95, 48], [240, 41], [127, 118], [183, 113], [141, 148], [150, 148], [149, 161], [145, 459], [228, 442]], "trg_kps": [[251, 74], [351, 68], [297, 134], [333, 132], [319, 156], [324, 155], [320, 168], [294, 403], [188, 445]], "kps_ids": ["2", "3", "4", "5", "6", "7", "8", "9", "13"], "mirror": 0, "viewpoint_variation": 1, "scale_variation": 0, "truncation": 0, "occlusion": 0}