{"pair_id": 22063, "filename": "022063-2010_000109-2010_005408:cat", "src_imname": "2010_000109.jpg", "trg_imname": "2010_005408.jpg", "src_imsize": [500, 465, 3], "trg_imsize": [500, 375, 3], "src_bndbox": [71, 40, 384, 464], "trg_bndbox": [99, 65, 448, 307], "category": "cat", "src_pose": "Unspecified", "trg_pose": "Left", "src_kps": [[376, 48], [337, 178], [275, 435], [165, 441], [237, 417], [290, 404]], "trg_kps": [[112, 168], [106, 223], [146, 271], [256, 257], [439, 216], [365, 72]], "kps_ids": ["3", "8", "10", "11", "12", "13"], "mirror": 0, "viewpoint_variation": 1, "scale_variation": 0, "truncation": 0, "occlusion": 0}