{"pair_id": 24291, "filename": "024291-2008_007361-2010_005188:chair", "src_imname": "2008_007361.jpg", "trg_imname": "2010_005188.jpg", "src_imsize": [500, 375, 3], "trg_imsize": [500, 375, 3], "src_bndbox": [264, 152, 362, 370], "trg_bndbox": [159, 147, 324, 364], "category": "chair", "src_pose": "Rear", "trg_pose": "Unspecified", "src_kps": [[357, 253], [342, 282], [356, 315], [336, 362], [341, 180], [278, 169]], "trg_kps": [[264, 287], [174, 260], [259, 363], [173, 330], [167, 155], [219, 136]], "kps_ids": ["0", "2", "4", "6", "8", "9"], "mirror": 0, "viewpoint_variation": 1, "scale_variation": 0, "truncation": 0, "occlusion": 3}