{"pair_id": 25286, "filename": "025286-2009_003116-2009_005300:chair", "src_imname": "2009_003116.jpg", "trg_imname": "2009_005300.jpg", "src_imsize": [500, 500, 3], "trg_imsize": [375, 500, 3], "src_bndbox": [130, 161, 475, 465], "trg_bndbox": [222, 263, 339, 461], "category": "chair", "src_pose": "Unspecified", "trg_pose": "Frontal", "src_kps": [[156, 324], [353, 332], [418, 328], [136, 441], [339, 457], [443, 179]], "trg_kps": [[228, 365], [330, 365], [319, 341], [223, 449], [328, 455], [322, 266]], "kps_ids": ["0", "1", "3", "4", "5", "9"], "mirror": 0, "viewpoint_variation": 0, "scale_variation": 2, "truncation": 0, "occlusion": 3}