{"pair_id": 27674, "filename": "027674-2008_008169-2010_001000:cow", "src_imname": "2008_008169.jpg", "trg_imname": "2010_001000.jpg", "src_imsize": [500, 300, 3], "trg_imsize": [500, 334, 3], "src_bndbox": [1, 13, 451, 300], "trg_bndbox": [41, 3, 500, 334], "category": "cow", "src_pose": "Right", "trg_pose": "Left", "src_kps": [[79, 66], [441, 54], [200, 124], [318, 115], [232, 198], [274, 195], [257, 226]], "trg_kps": [[51, 93], [327, 47], [114, 110], [231, 100], [113, 175], [148, 170], [134, 203]], "kps_ids": ["2", "3", "4", "5", "6", "7", "8"], "mirror": 0, "viewpoint_variation": 1, "scale_variation": 0, "truncation": 3, "occlusion": 0}