{"pair_id": 27722, "filename": "027722-2008_008428-2009_001475:cow", "src_imname": "2008_008428.jpg", "trg_imname": "2009_001475.jpg", "src_imsize": [481, 500, 3], "trg_imsize": [500, 332, 3], "src_bndbox": [30, 50, 454, 479], "trg_bndbox": [33, 25, 497, 332], "category": "cow", "src_pose": "Right", "trg_pose": "Frontal", "src_kps": [[239, 128], [180, 114], [260, 146], [350, 149], [290, 244], [328, 247]], "trg_kps": [[166, 106], [36, 111], [195, 120], [334, 117], [249, 244], [293, 246]], "kps_ids": ["0", "2", "4", "5", "6", "7"], "mirror": 0, "viewpoint_variation": 0, "scale_variation": 0, "truncation": 2, "occlusion": 0}