{"pair_id": 27747, "filename": "027747-2008_008428-2011_001159:cow", "src_imname": "2008_008428.jpg", "trg_imname": "2011_001159.jpg", "src_imsize": [481, 500, 3], "trg_imsize": [500, 500, 3], "src_bndbox": [30, 50, 454, 479], "trg_bndbox": [73, 193, 477, 443], "category": "cow", "src_pose": "Right", "trg_pose": "Left", "src_kps": [[350, 149], [328, 247], [211, 463], [305, 452], [98, 395], [292, 381], [88, 324], [108, 312]], "trg_kps": [[113, 300], [81, 345], [220, 425], [235, 444], [405, 427], [238, 395], [407, 355], [435, 355]], "kps_ids": ["5", "7", "9", "10", "11", "16", "17", "18"], "mirror": 0, "viewpoint_variation": 1, "scale_variation": 0, "truncation": 0, "occlusion": 0}