{"pair_id": 29214, "filename": "029214-2010_004322-2008_008121:cow", "src_imname": "2010_004322.jpg", "trg_imname": "2008_008121.jpg", "src_imsize": [500, 375, 3], "trg_imsize": [375, 500, 3], "src_bndbox": [10, 24, 500, 374], "trg_bndbox": [1, 191, 302, 500], "category": "cow", "src_pose": "Frontal", "trg_pose": "Right", "src_kps": [[114, 115], [489, 125], [207, 331], [243, 361]], "trg_kps": [[253, 195], [235, 195], [298, 275], [289, 286]], "kps_ids": ["2", "3", "6", "8"], "mirror": 0, "viewpoint_variation": 2, "scale_variation": 0, "truncation": 3, "occlusion": 2}