{"pair_id": 29597, "filename": "029597-2011_001354-2008_005714:cow", "src_imname": "2011_001354.jpg", "trg_imname": "2008_005714.jpg", "src_imsize": [500, 375, 3], "trg_imsize": [500, 375, 3], "src_bndbox": [70, 62, 420, 344], "trg_bndbox": [43, 46, 298, 218], "category": "cow", "src_pose": "Frontal", "trg_pose": "Right", "src_kps": [[160, 143], [291, 139], [116, 145], [328, 137], [252, 230], [284, 231], [265, 252], [107, 313]], "trg_kps": [[230, 75], [280, 68], [212, 74], [294, 66], [245, 108], [259, 111], [252, 120], [191, 211]], "kps_ids": ["0", "1", "2", "3", "6", "7", "8", "15"], "mirror": 0, "viewpoint_variation": 1, "scale_variation": 1, "truncation": 2, "occlusion": 2}