{"pair_id": 30178, "filename": "030178-2007_006444-2009_002586:dog", "src_imname": "2007_006444.jpg", "trg_imname": "2009_002586.jpg", "src_imsize": [500, 375, 3], "trg_imsize": [500, 375, 3], "src_bndbox": [134, 146, 271, 364], "trg_bndbox": [74, 72, 369, 357], "category": "dog", "src_pose": "Rear", "trg_pose": "Unspecified", "src_kps": [[268, 195], [253, 151], [240, 174], [239, 286], [250, 271], [245, 310], [191, 319], [237, 207]], "trg_kps": [[251, 108], [353, 141], [318, 87], [225, 347], [259, 324], [78, 291], [107, 149], [258, 150]], "kps_ids": ["2", "6", "7", "9", "10", "11", "14", "15"], "mirror": 0, "viewpoint_variation": 1, "scale_variation": 1, "truncation": 0, "occlusion": 0}