{"pair_id": 30480, "filename": "030480-2008_003645-2010_001665:dog", "src_imname": "2008_003645.jpg", "trg_imname": "2010_001665.jpg", "src_imsize": [500, 474, 3], "trg_imsize": [500, 375, 3], "src_bndbox": [5, 63, 436, 470], "trg_bndbox": [160, 48, 349, 340], "category": "dog", "src_pose": "Right", "trg_pose": "Frontal", "src_kps": [[328, 171], [359, 126], [424, 146], [329, 80], [420, 171], [59, 387]], "trg_kps": [[189, 136], [222, 143], [250, 176], [248, 113], [247, 190], [325, 83]], "kps_ids": ["2", "4", "6", "7", "8", "14"], "mirror": 0, "viewpoint_variation": 1, "scale_variation": 1, "truncation": 0, "occlusion": 0}