{"pair_id": 30622, "filename": "030622-2008_004833-2008_005436:dog", "src_imname": "2008_004833.jpg", "trg_imname": "2008_005436.jpg", "src_imsize": [500, 369, 3], "trg_imsize": [500, 375, 3], "src_bndbox": [18, 51, 453, 362], "trg_bndbox": [2, 26, 328, 375], "category": "dog", "src_pose": "Right", "trg_pose": "Right", "src_kps": [[233, 83], [376, 85], [269, 98], [312, 99], [259, 119], [297, 68], [263, 140], [135, 134]], "trg_kps": [[193, 114], [294, 97], [201, 63], [242, 66], [203, 105], [226, 39], [208, 117], [86, 168]], "kps_ids": ["2", "3", "4", "5", "6", "7", "8", "14"], "mirror": 0, "viewpoint_variation": 0, "scale_variation": 0, "truncation": 2, "occlusion": 2}