{"pair_id": 31244, "filename": "031244-2009_002324-2008_003276:dog", "src_imname": "2009_002324.jpg", "trg_imname": "2008_003276.jpg", "src_imsize": [500, 358, 3], "trg_imsize": [500, 333, 3], "src_bndbox": [131, 97, 399, 265], "trg_bndbox": [181, 134, 375, 284], "category": "dog", "src_pose": "Left", "trg_pose": "Rear", "src_kps": [[175, 136], [136, 149], [157, 119], [214, 253], [295, 218], [329, 242], [390, 112], [335, 120], [194, 127]], "trg_kps": [[220, 141], [204, 141], [232, 146], [187, 216], [299, 259], [245, 275], [369, 269], [313, 222], [245, 157]], "kps_ids": ["3", "6", "7", "10", "11", "12", "13", "14", "15"], "mirror": 0, "viewpoint_variation": 1, "scale_variation": 0, "truncation": 0, "occlusion": 0}