{"pair_id": 31356, "filename": "031356-2009_002586-2008_000620:dog", "src_imname": "2009_002586.jpg", "trg_imname": "2008_000620.jpg", "src_imsize": [500, 375, 3], "trg_imsize": [500, 337, 3], "src_bndbox": [74, 72, 369, 357], "trg_bndbox": [205, 208, 327, 337], "category": "dog", "src_pose": "Unspecified", "trg_pose": "Right", "src_kps": [[251, 108], [311, 112], [353, 141], [318, 87], [344, 154], [225, 347], [259, 324], [78, 291], [146, 283], [107, 149]], "trg_kps": [[289, 209], [308, 223], [322, 233], [307, 211], [315, 237], [288, 312], [269, 309], [247, 336], [209, 327], [220, 244]], "kps_ids": ["2", "4", "6", "7", "8", "9", "10", "11", "12", "14"], "mirror": 0, "viewpoint_variation": 1, "scale_variation": 2, "truncation": 0, "occlusion": 2}