{"pair_id": 31597, "filename": "031597-2009_004507-2009_000923:dog", "src_imname": "2009_004507.jpg", "trg_imname": "2009_000923.jpg", "src_imsize": [500, 334, 3], "trg_imsize": [333, 500, 3], "src_bndbox": [87, 29, 408, 329], "trg_bndbox": [124, 143, 333, 500], "category": "dog", "src_pose": "Left", "trg_pose": "Frontal", "src_kps": [[97, 70], [137, 78], [104, 115], [121, 42], [104, 124], [200, 259], [134, 291], [269, 314]], "trg_kps": [[179, 218], [227, 202], [202, 237], [204, 159], [211, 255], [173, 487], [293, 461], [323, 441]], "kps_ids": ["4", "5", "6", "7", "8", "9", "10", "12"], "mirror": 0, "viewpoint_variation": 1, "scale_variation": 0, "truncation": 0, "occlusion": 2}