{"pair_id": 32496, "filename": "032496-2010_001976-2008_000620:dog", "src_imname": "2010_001976.jpg", "trg_imname": "2008_000620.jpg", "src_imsize": [500, 375, 3], "trg_imsize": [500, 337, 3], "src_bndbox": [166, 95, 358, 314], "trg_bndbox": [205, 208, 327, 337], "category": "dog", "src_pose": "Unspecified", "trg_pose": "Right", "src_kps": [[179, 129], [177, 197], [194, 210], [200, 171], [194, 225], [203, 264], [263, 301], [299, 216], [337, 246], [335, 102]], "trg_kps": [[289, 209], [308, 223], [322, 233], [307, 211], [315, 237], [288, 312], [269, 309], [247, 336], [209, 327], [220, 244]], "kps_ids": ["2", "4", "6", "7", "8", "9", "10", "11", "12", "14"], "mirror": 0, "viewpoint_variation": 2, "scale_variation": 1, "truncation": 0, "occlusion": 2}