{"pair_id": 33566, "filename": "033566-2007_001724-2009_003734:horse", "src_imname": "2007_001724.jpg", "trg_imname": "2009_003734.jpg", "src_imsize": [275, 315, 3], "trg_imsize": [500, 375, 3], "src_bndbox": [35, 15, 219, 302], "trg_bndbox": [221, 143, 397, 256], "category": "horse", "src_pose": "Unspecified", "trg_pose": "Left", "src_kps": [[187, 41], [213, 172], [203, 189], [162, 289], [190, 261], [90, 231], [121, 220], [70, 25], [156, 236], [185, 209]], "trg_kps": [[224, 158], [241, 187], [243, 190], [295, 240], [252, 230], [349, 256], [367, 255], [366, 168], [288, 215], [263, 206]], "kps_ids": ["3", "7", "8", "10", "11", "12", "13", "15", "16", "17"], "mirror": 0, "viewpoint_variation": 1, "scale_variation": 1, "truncation": 0, "occlusion": 2}