{"pair_id": 33615, "filename": "033615-2007_001960-2008_005792:horse", "src_imname": "2007_001960.jpg", "trg_imname": "2008_005792.jpg", "src_imsize": [329, 500, 3], "trg_imsize": [433, 342, 3], "src_bndbox": [108, 138, 264, 332], "trg_bndbox": [86, 100, 430, 294], "category": "horse", "src_pose": "Unspecified", "trg_pose": "Left", "src_kps": [[132, 176], [120, 211], [116, 218], [127, 151], [156, 319], [198, 320], [193, 310], [224, 312], [266, 239], [240, 192], [130, 283], [176, 300], [202, 285], [242, 271]], "trg_kps": [[106, 128], [87, 151], [91, 155], [126, 109], [139, 261], [197, 274], [251, 304], [220, 285], [426, 197], [306, 185], [135, 232], [151, 267], [277, 270], [262, 262]], "kps_ids": ["5", "7", "8", "9", "10", "11", "12", "13", "14", "15", "16", "17", "18", "19"], "mirror": 0, "viewpoint_variation": 1, "scale_variation": 1, "truncation": 0, "occlusion": 2}