{"pair_id": 34690, "filename": "034690-2008_001682-2007_006445:horse", "src_imname": "2008_001682.jpg", "trg_imname": "2007_006445.jpg", "src_imsize": [500, 375, 3], "trg_imsize": [443, 480, 3], "src_bndbox": [148, 131, 317, 302], "trg_bndbox": [65, 156, 401, 459], "category": "horse", "src_pose": "Right", "trg_pose": "Right", "src_kps": [[301, 139], [301, 133], [312, 132], [299, 151], [305, 173], [305, 142], [270, 301], [279, 295], [180, 293], [165, 287], [172, 179], [268, 268], [275, 264], [174, 266], [168, 253]], "trg_kps": [[372, 185], [373, 172], [393, 175], [364, 215], [367, 266], [380, 194], [305, 312], [307, 294], [67, 454], [93, 452], [123, 250], [318, 260], [346, 262], [96, 377], [126, 379]], "kps_ids": ["0", "2", "3", "4", "6", "9", "10", "11", "12", "13", "15", "16", "17", "18", "19"], "mirror": 0, "viewpoint_variation": 0, "scale_variation": 1, "truncation": 0, "occlusion": 0}