{"pair_id": 35123, "filename": "035123-2008_003018-2009_003768:horse", "src_imname": "2008_003018.jpg", "trg_imname": "2009_003768.jpg", "src_imsize": [346, 500, 3], "trg_imsize": [355, 500, 3], "src_bndbox": [32, 22, 317, 459], "trg_bndbox": [20, 158, 324, 426], "category": "horse", "src_pose": "Left", "trg_pose": "Right", "src_kps": [[173, 27], [102, 63], [148, 30], [42, 144], [84, 101], [169, 425], [203, 451], [256, 308], [84, 117], [135, 97], [200, 368]], "trg_kps": [[252, 162], [317, 190], [264, 175], [259, 395], [220, 397], [113, 407], [29, 406], [75, 256], [283, 346], [229, 362], [102, 364]], "kps_ids": ["3", "8", "9", "10", "11", "12", "13", "15", "16", "17", "18"], "mirror": 0, "viewpoint_variation": 2, "scale_variation": 0, "truncation": 0, "occlusion": 2}