{"pair_id": 35271, "filename": "035271-2008_003380-2008_002697:horse", "src_imname": "2008_003380.jpg", "trg_imname": "2008_002697.jpg", "src_imsize": [500, 333, 3], "trg_imsize": [500, 375, 3], "src_bndbox": [251, 186, 299, 214], "trg_bndbox": [69, 116, 333, 347], "category": "horse", "src_pose": "Right", "trg_pose": "Left", "src_kps": [[297, 194], [293, 189], [294, 211], [279, 212], [265, 212], [254, 211], [259, 195], [279, 210], [264, 210], [254, 208]], "trg_kps": [[90, 212], [83, 139], [234, 306], [209, 323], [282, 311], [319, 312], [285, 140], [203, 276], [280, 258], [308, 256]], "kps_ids": ["8", "9", "10", "11", "12", "13", "15", "17", "18", "19"], "mirror": 0, "viewpoint_variation": 1, "scale_variation": 2, "truncation": 0, "occlusion": 1}