{"pair_id": 35883, "filename": "035883-2009_000312-2008_000696:horse", "src_imname": "2009_000312.jpg", "trg_imname": "2008_000696.jpg", "src_imsize": [500, 375, 3], "trg_imsize": [500, 286, 3], "src_bndbox": [175, 36, 500, 375], "trg_bndbox": [208, 9, 284, 226], "category": "horse", "src_pose": "Left", "trg_pose": "Frontal", "src_kps": [[273, 70], [286, 37], [276, 47], [224, 133], [180, 218], [192, 237], [256, 64]], "trg_kps": [[274, 15], [255, 9], [277, 10], [274, 38], [262, 69], [259, 72], [265, 16]], "kps_ids": ["1", "2", "3", "5", "7", "8", "9"], "mirror": 0, "viewpoint_variation": 1, "scale_variation": 2, "truncation": 1, "occlusion": 1}