{"pair_id": 36305, "filename": "036305-2010_000461-2009_003294:horse", "src_imname": "2010_000461.jpg", "trg_imname": "2009_003294.jpg", "src_imsize": [500, 375, 3], "trg_imsize": [500, 333, 3], "src_bndbox": [149, 109, 500, 375], "trg_bndbox": [207, 38, 393, 310], "category": "horse", "src_pose": "Left", "trg_pose": "Unspecified", "src_kps": [[185, 155], [154, 158], [276, 319], [188, 170]], "trg_kps": [[239, 42], [212, 45], [206, 100], [228, 51]], "kps_ids": ["2", "3", "8", "9"], "mirror": 0, "viewpoint_variation": 0, "scale_variation": 0, "truncation": 1, "occlusion": 3}