{"pair_id": 37439, "filename": "037439-2008_006857-2010_005346:motorbike", "src_imname": "2008_006857.jpg", "trg_imname": "2010_005346.jpg", "src_imsize": [333, 500, 3], "trg_imsize": [500, 333, 3], "src_bndbox": [139, 116, 304, 414], "trg_bndbox": [46, 58, 383, 296], "category": "motorbike", "src_pose": "Unspecified", "trg_pose": "Right", "src_kps": [[154, 228], [143, 202], [252, 164], [258, 371], [206, 141]], "trg_kps": [[227, 144], [281, 104], [332, 256], [126, 236], [352, 217]], "kps_ids": ["2", "3", "6", "7", "11"], "mirror": 0, "viewpoint_variation": 0, "scale_variation": 0, "truncation": 0, "occlusion": 1}