{"pair_id": 37640, "filename": "037640-2008_007138-2008_007241:motorbike", "src_imname": "2008_007138.jpg", "trg_imname": "2008_007241.jpg", "src_imsize": [500, 375, 3], "trg_imsize": [500, 375, 3], "src_bndbox": [133, 1, 500, 277], "trg_bndbox": [101, 23, 376, 362], "category": "motorbike", "src_pose": "Left", "trg_pose": "Unspecified", "src_kps": [[295, 36], [373, 51], [295, 63], [226, 102], [194, 225], [446, 193], [151, 172], [258, 224]], "trg_kps": [[229, 40], [284, 60], [220, 76], [307, 135], [302, 291], [145, 189], [351, 232], [235, 262]], "kps_ids": ["0", "1", "2", "4", "6", "7", "11", "12"], "mirror": 0, "viewpoint_variation": 1, "scale_variation": 0, "truncation": 1, "occlusion": 1}