{"pair_id": 38275, "filename": "038275-2009_002763-2009_003539:motorbike", "src_imname": "2009_002763.jpg", "trg_imname": "2009_003539.jpg", "src_imsize": [500, 375, 3], "trg_imsize": [500, 414, 3], "src_bndbox": [58, 54, 419, 297], "trg_bndbox": [112, 48, 386, 392], "category": "motorbike", "src_pose": "Left", "trg_pose": "Unspecified", "src_kps": [[209, 131], [189, 123], [116, 146], [99, 244], [342, 244], [364, 243]], "trg_kps": [[170, 54], [334, 105], [226, 105], [171, 295], [346, 205], [365, 227]], "kps_ids": ["2", "3", "4", "6", "7", "10"], "mirror": 0, "viewpoint_variation": 0, "scale_variation": 0, "truncation": 0, "occlusion": 0}