{"pair_id": 38526, "filename": "038526-2009_005086-2011_003063:motorbike", "src_imname": "2009_005086.jpg", "trg_imname": "2011_003063.jpg", "src_imsize": [500, 367, 3], "trg_imsize": [500, 375, 3], "src_bndbox": [241, 179, 466, 333], "trg_bndbox": [73, 16, 499, 352], "category": "motorbike", "src_pose": "Left", "trg_pose": "Unspecified", "src_kps": [[323, 209], [289, 241], [276, 303], [421, 286], [246, 286], [314, 309]], "trg_kps": [[209, 47], [373, 45], [401, 269], [127, 137], [493, 173], [291, 258]], "kps_ids": ["2", "4", "6", "7", "11", "12"], "mirror": 0, "viewpoint_variation": 1, "scale_variation": 2, "truncation": 0, "occlusion": 0}