{"pair_id": 38656, "filename": "038656-2010_000695-2008_006323:motorbike", "src_imname": "2010_000695.jpg", "trg_imname": "2008_006323.jpg", "src_imsize": [500, 375, 3], "trg_imsize": [500, 334, 3], "src_bndbox": [162, 128, 345, 232], "trg_bndbox": [77, 5, 383, 334], "category": "motorbike", "src_pose": "Right", "trg_pose": "Frontal", "src_kps": [[300, 165], [315, 208], [336, 194]], "trg_kps": [[199, 149], [108, 332], [168, 277]], "kps_ids": ["4", "6", "11"], "mirror": 0, "viewpoint_variation": 1, "scale_variation": 2, "truncation": 2, "occlusion": 1}