{"pair_id": 39546, "filename": "039546-2011_000651-2011_002097:motorbike", "src_imname": "2011_000651.jpg", "trg_imname": "2011_002097.jpg", "src_imsize": [389, 500, 3], "trg_imsize": [500, 375, 3], "src_bndbox": [55, 79, 342, 441], "trg_bndbox": [106, 77, 442, 374], "category": "motorbike", "src_pose": "Unspecified", "trg_pose": "Unspecified", "src_kps": [[146, 229], [117, 381], [289, 258], [103, 326]], "trg_kps": [[197, 151], [195, 293], [398, 269], [114, 185]], "kps_ids": ["4", "6", "7", "11"], "mirror": 0, "viewpoint_variation": 0, "scale_variation": 0, "truncation": 0, "occlusion": 2}