{"pair_id": 42027, "filename": "042027-2008_000645-2007_003621:person", "src_imname": "2008_000645.jpg", "trg_imname": "2007_003621.jpg", "src_imsize": [320, 240, 3], "trg_imsize": [500, 343, 3], "src_bndbox": [64, 19, 261, 240], "trg_bndbox": [249, 72, 334, 224], "category": "person", "src_pose": "Rear", "trg_pose": "Unspecified", "src_kps": [[117, 74], [151, 63], [174, 72], [233, 137], [226, 190], [246, 213]], "trg_kps": [[304, 89], [322, 110], [320, 141], [294, 189], [258, 202], [270, 217]], "kps_ids": ["6", "8", "10", "14", "16", "18"], "mirror": 0, "viewpoint_variation": 0, "scale_variation": 1, "truncation": 0, "occlusion": 0}