{"pair_id": 42444, "filename": "042444-2008_001167-2008_000950:person", "src_imname": "2008_001167.jpg", "trg_imname": "2008_000950.jpg", "src_imsize": [500, 365, 3], "trg_imsize": [500, 375, 3], "src_bndbox": [408, 76, 475, 295], "trg_bndbox": [69, 27, 500, 375], "category": "person", "src_pose": "Left", "trg_pose": "Left", "src_kps": [[427, 91], [425, 94], [429, 106], [427, 102], [450, 121]], "trg_kps": [[160, 208], [116, 262], [179, 332], [149, 293], [420, 364]], "kps_ids": ["1", "4", "5", "7", "9"], "mirror": 0, "viewpoint_variation": 0, "scale_variation": 2, "truncation": 2, "occlusion": 2}