{"pair_id": 42471, "filename": "042471-2008_001257-2007_003742:person", "src_imname": "2008_001257.jpg", "trg_imname": "2007_003742.jpg", "src_imsize": [375, 500, 3], "trg_imsize": [240, 320, 3], "src_bndbox": [81, 50, 228, 491], "trg_bndbox": [2, 24, 181, 236], "category": "person", "src_pose": "Rear", "trg_pose": "Frontal", "src_kps": [[179, 159], [122, 194]], "trg_kps": [[95, 90], [158, 121]], "kps_ids": ["6", "9"], "mirror": 0, "viewpoint_variation": 2, "scale_variation": 0, "truncation": 2, "occlusion": 0}