{"pair_id": 43085, "filename": "043085-2008_001460-2011_001022:pottedplant", "src_imname": "2008_001460.jpg", "trg_imname": "2011_001022.jpg", "src_imsize": [500, 367, 3], "trg_imsize": [500, 333, 3], "src_bndbox": [112, 1, 493, 367], "trg_bndbox": [218, 1, 326, 295], "category": "pottedplant", "src_pose": "Unspecified", "trg_pose": "Unspecified", "src_kps": [[226, 135], [475, 128], [342, 185], [235, 238], [458, 248], [274, 323], [346, 351], [425, 327]], "trg_kps": [[220, 198], [318, 195], [267, 208], [226, 240], [319, 236], [228, 274], [273, 289], [316, 276]], "kps_ids": ["0", "2", "3", "4", "5", "6", "7", "8"], "mirror": 0, "viewpoint_variation": 0, "scale_variation": 2, "truncation": 1, "occlusion": 0}