{"pair_id": 45347, "filename": "045347-2007_000676-2008_006477:sheep", "src_imname": "2007_000676.jpg", "trg_imname": "2008_006477.jpg", "src_imsize": [500, 375, 3], "trg_imsize": [500, 399, 3], "src_bndbox": [59, 94, 472, 270], "trg_bndbox": [1, 104, 291, 399], "category": "sheep", "src_pose": "Left", "trg_pose": "Right", "src_kps": [[90, 126], [76, 187], [74, 199]], "trg_kps": [[96, 132], [278, 136], [273, 161]], "kps_ids": ["2", "7", "8"], "mirror": 0, "viewpoint_variation": 2, "scale_variation": 0, "truncation": 2, "occlusion": 0}