{"pair_id": 46155, "filename": "046155-2008_008744-2009_005193:sheep", "src_imname": "2008_008744.jpg", "trg_imname": "2009_005193.jpg", "src_imsize": [500, 375, 3], "trg_imsize": [500, 375, 3], "src_bndbox": [1, 125, 288, 338], "trg_bndbox": [94, 27, 417, 330], "category": "sheep", "src_pose": "Right", "trg_pose": "Right", "src_kps": [[263, 196], [271, 202], [152, 286], [177, 274], [56, 332], [158, 255], [46, 296]], "trg_kps": [[375, 277], [389, 276], [269, 325], [319, 302], [128, 286], [266, 261], [129, 217]], "kps_ids": ["2", "4", "9", "10", "11", "15", "17"], "mirror": 0, "viewpoint_variation": 0, "scale_variation": 0, "truncation": 0, "occlusion": 1}