{"pair_id": 48015, "filename": "048015-2010_003491-2010_000002:sheep", "src_imname": "2010_003491.jpg", "trg_imname": "2010_000002.jpg", "src_imsize": [500, 375, 3], "trg_imsize": [500, 430, 3], "src_bndbox": [143, 276, 286, 358], "trg_bndbox": [102, 46, 411, 400], "category": "sheep", "src_pose": "Unspecified", "trg_pose": "Unspecified", "src_kps": [[259, 312], [285, 342], [275, 335], [251, 352], [255, 342], [225, 349]], "trg_kps": [[110, 124], [227, 375], [268, 394], [315, 306], [221, 318], [318, 267]], "kps_ids": ["8", "9", "10", "11", "15", "17"], "mirror": 0, "viewpoint_variation": 2, "scale_variation": 2, "truncation": 0, "occlusion": 0}