{"pair_id": 48749, "filename": "048749-2008_004610-2008_003571:train", "src_imname": "2008_004610.jpg", "trg_imname": "2008_003571.jpg", "src_imsize": [500, 321, 3], "trg_imsize": [500, 333, 3], "src_bndbox": [61, 50, 411, 298], "trg_bndbox": [105, 157, 366, 252], "category": "train", "src_pose": "Frontal", "trg_pose": "Unspecified", "src_kps": [[218, 59], [128, 59], [221, 207], [80, 205], [242, 81], [105, 81], [239, 110], [105, 107], [174, 78], [159, 78], [183, 193], [98, 189]], "trg_kps": [[358, 167], [294, 169], [363, 226], [304, 227], [355, 172], [304, 170], [357, 179], [305, 179], [336, 167], [330, 167], [353, 228], [318, 230]], "kps_ids": ["0", "1", "2", "3", "8", "9", "10", "11", "12", "13", "16", "17"], "mirror": 0, "viewpoint_variation": 0, "scale_variation": 1, "truncation": 0, "occlusion": 2}