{"pair_id": 49589, "filename": "049589-2009_001359-2011_000627:train", "src_imname": "2009_001359.jpg", "trg_imname": "2011_000627.jpg", "src_imsize": [500, 333, 3], "trg_imsize": [500, 375, 3], "src_bndbox": [158, 104, 462, 265], "trg_bndbox": [46, 143, 486, 256], "category": "train", "src_pose": "Unspecified", "trg_pose": "Left", "src_kps": [[444, 119], [454, 217], [444, 137], [448, 178], [450, 200]], "trg_kps": [[106, 152], [78, 213], [104, 163], [105, 171], [70, 198]], "kps_ids": ["0", "2", "8", "10", "16"], "mirror": 0, "viewpoint_variation": 1, "scale_variation": 0, "truncation": 0, "occlusion": 0}