{"pair_id": 49689, "filename": "049689-2009_002197-2010_002697:train", "src_imname": "2009_002197.jpg", "trg_imname": "2010_002697.jpg", "src_imsize": [500, 325, 3], "trg_imsize": [500, 332, 3], "src_bndbox": [194, 29, 397, 188], "trg_bndbox": [27, 62, 500, 264], "category": "train", "src_pose": "Unspecified", "trg_pose": "Unspecified", "src_kps": [[297, 59], [218, 56], [270, 169], [391, 36], [392, 58], [277, 64], [229, 66], [267, 101], [269, 137], [207, 134]], "trg_kps": [[173, 77], [95, 84], [177, 200], [497, 172], [497, 183], [179, 97], [85, 101], [183, 118], [143, 165], [54, 168]], "kps_ids": ["0", "1", "2", "4", "6", "8", "9", "10", "16", "17"], "mirror": 0, "viewpoint_variation": 0, "scale_variation": 1, "truncation": 0, "occlusion": 1}