{"pair_id": 50887, "filename": "050887-2010_004193-2009_002265:train", "src_imname": "2010_004193.jpg", "trg_imname": "2009_002265.jpg", "src_imsize": [500, 378, 3], "trg_imsize": [500, 333, 3], "src_bndbox": [44, 165, 476, 321], "trg_bndbox": [31, 36, 366, 288], "category": "train", "src_pose": "Left", "trg_pose": "Frontal", "src_kps": [[88, 199], [61, 192], [77, 302], [51, 280], [92, 212], [96, 238], [81, 258]], "trg_kps": [[345, 159], [270, 159], [356, 250], [285, 248], [331, 164], [339, 192], [353, 235]], "kps_ids": ["0", "1", "2", "3", "8", "10", "16"], "mirror": 0, "viewpoint_variation": 1, "scale_variation": 0, "truncation": 0, "occlusion": 2}