{"pair_id": 52706, "filename": "052706-2009_000791-2008_003213:tvmonitor", "src_imname": "2009_000791.jpg", "trg_imname": "2008_003213.jpg", "src_imsize": [500, 375, 3], "trg_imsize": [400, 300, 3], "src_bndbox": [82, 1, 322, 198], "trg_bndbox": [1, 51, 116, 180], "category": "tvmonitor", "src_pose": "Frontal", "trg_pose": "Frontal", "src_kps": [[314, 71], [307, 150], [203, 153], [299, 65], [293, 142], [203, 143]], "trg_kps": [[115, 111], [118, 164], [59, 173], [104, 110], [105, 146], [55, 151]], "kps_ids": ["3", "4", "5", "11", "12", "13"], "mirror": 0, "viewpoint_variation": 0, "scale_variation": 1, "truncation": 3, "occlusion": 0}