{"pair_id": 52868, "filename": "052868-2009_001682-2008_002680:tvmonitor", "src_imname": "2009_001682.jpg", "trg_imname": "2008_002680.jpg", "src_imsize": [500, 375, 3], "trg_imsize": [342, 458, 3], "src_bndbox": [165, 126, 352, 250], "trg_bndbox": [37, 34, 290, 237], "category": "tvmonitor", "src_pose": "Unspecified", "trg_pose": "Frontal", "src_kps": [[208, 130], [276, 133], [340, 149], [344, 197], [338, 244], [284, 249], [207, 240], [206, 190], [226, 144], [281, 147], [324, 158], [332, 195], [330, 236], [281, 240], [226, 230], [218, 189]], "trg_kps": [[41, 41], [162, 34], [287, 35], [289, 124], [286, 228], [166, 235], [50, 232], [42, 128], [55, 52], [161, 48], [274, 48], [276, 111], [273, 181], [168, 181], [58, 181], [56, 117]], "kps_ids": ["0", "1", "2", "3", "4", "5", "6", "7", "8", "9", "10", "11", "12", "13", "14", "15"], "mirror": 0, "viewpoint_variation": 0, "scale_variation": 1, "truncation": 0, "occlusion": 0}