{"filename": "2010_003725.jpg", "src_database": "The VOC2010 Database", "src_annotation": "PASCAL VOC2010", "src_image": "flickr", "image_width": 500, "image_height": 333, "image_depth": 3, "category": "sheep", "pose": "Unspecified", "truncated": 1, "occluded": 0, "difficult": 0, "bndbox": [33, 1, 439, 333], "kps": {"0": [117, 178], "1": [237, 64], "2": [31, 206], "3": null, "4": [116, 159], "5": [220, 65], "6": [167, 154], "7": [191, 135], "8": [207, 172], "9": [380, 330], "10": [450, 269], "11": null, "12": null, "13": null, "14": null, "15": null, "16": null, "17": null, "18": null, "19": null, "20": null, "21": null, "22": null, "23": null, "24": null, "25": null, "26": null, "27": null, "28": null, "29": null}, "azimuth_id": 7}